nonebot_plugin_tea_silencer/__init__.py
nonebot_plugin_tea_silencer/config.py
nonebot_plugin_tea_silencer/silencer/filter/侮辱.json
nonebot_plugin_tea_silencer/silencer/filter/广告.json
nonebot_plugin_tea_silencer/silencer/filter/涩涩.json
nonebot_plugin_tea_silencer/silencer/filter/键政.json
nonebot_plugin_tea_silencer/silencer/filter/非法.json
nonebot_plugin_tea_silencer/silencer/flymo/提示.json
nonebot_plugin_tea_silencer/silencer/flymo/棉花.json
nonebot_plugin_tea_silencer/silencer/flymo/阴阳.json
nonebot_plugin_tea_silencer/silencer/flymo/飞马.json
nonebot_plugin_tea_silencer/silencer.py
nonebot_plugin_tea_silencer-1.0.2.dist-info/LICENSE
nonebot_plugin_tea_silencer-1.0.2.dist-info/METADATA
nonebot_plugin_tea_silencer-1.0.2.dist-info/WHEEL
nonebot_plugin_tea_silencer-1.0.2.dist-info/RECORD
