Metadata-Version: 2.1
Name: nonebot-plugin-tea-silencer
Version: 1.0.2
Summary: 又一个消息审查插件，可针对不同程度嘴臭配置自动屏蔽、回应规则，支持指令拉黑群或用户。
Home-page: https://github.com/youlanan/nonebot-plugin-tea-silencer
License: MIT
Keywords: NoneBot,silencer
Author: 悠岚岸
Requires-Python: >=3.9,<4.0
Classifier: License :: OSI Approved :: MIT License
Classifier: Programming Language :: Python :: 3
Classifier: Programming Language :: Python :: 3.9
Classifier: Programming Language :: Python :: 3.10
Classifier: Programming Language :: Python :: 3.11
Classifier: Programming Language :: Python :: 3.12
Requires-Dist: nonebot-adapter-onebot (>=2.2.0,<3.0.0)
Requires-Dist: nonebot2 (>=2.2.1,<3.0.0)
Requires-Dist: nonebot_plugin_localstore (>=0.7.0)
Requires-Dist: pydantic (>=2.7.1,<3.0.0)
Project-URL: Repository, https://github.com/youlanan/nonebot-plugin-tea-silencer
